devtools_jwt/__init__.py
devtools_jwt-1.0.1.dist-info/METADATA
devtools_jwt-1.0.1.dist-info/WHEEL
devtools_jwt-1.0.1.dist-info/top_level.txt
devtools_jwt-1.0.1.dist-info/RECORD
