Metadata-Version: 2.1
Name: devtools-jwt
Version: 1.0.1
Summary: JWT token decoder
Home-page: https://devtools.at/tools/jwt-decoder
Author: DevTools.at
Author-email: hello@devtools.at
Project-URL: Homepage, https://devtools.at/tools/jwt-decoder
Project-URL: Repository, https://github.com/devtools-at/jwt-decoder
Classifier: Development Status :: 4 - Beta
Classifier: Intended Audience :: Developers
Classifier: License :: OSI Approved :: MIT License
Classifier: Programming Language :: Python :: 3
Requires-Python: >=3.8
